Workbook

Sheet Sheet1
A1: Parameter | B1: Value
A2: Selling Price | B2: 800
A3: Product Cost (COGS) | B3: 280
A4: Referral Fee % | B4: 0.12
A5: Ad Spend | B5: 300000
A6: Ad Units | B6: 1500
A7: Organic Units | B7: 2000
A8: Fixed Cost | B8: 150000

Sheet Sheet2
A1: Metric | B1: Formula | C1: Result
A2: Gross Margin | B2: SP - COGS | C2: =Sheet1!B2-Sheet1!B3 -> 520
A3: Amazon Fee | B3: SP × Fee% | C3: =Sheet1!B2*Sheet1!B4 -> 96
A4: Ad Cost Per Unit | B4: Ad Spend ÷ Ad Units | C4: =VALUE(Sheet1!B5)/VALUE(Sheet1!B6) -> 200
A5: Net Margin Per Ad Unit | B5: Gross Margin - Amazon Fee - Ad Cost | C5: =C2-C3-C4 -> 224
A6: Organic Margin | B6: Gross Margin - Amazon Fee | C6: =C2-C3 -> 424

Sheet Sheet3
A1: Metric | B1: Formula | C1: Value
A2: Ad Revenue | B2: SP × Ad Units | C2: =VALUE(Sheet1!B2)*VALUE(Sheet1!B6) -> 1200000
A3: Organic Revenue | B3: SP × Organic Units | C3: =VALUE(Sheet1!B2)*VALUE(Sheet1!B7) -> 1600000
A4: Total Revenue | B4: Ad Revenue + Organic Revenue | C4: =SUM(C2+C3) -> 2800000
A5: Ad Profit | B5: Net Margin × Ad Units | C5: =VALUE(Sheet2!C5)*VALUE(Sheet1!B6) -> 336000
A6: Organic Profit | B6: Organic Margin × Organic Units | C6: =Sheet2!C6*Sheet1!B7 -> 848000
A7: Total Profit Before Fixed Cost | B7: Ad Profit + Organic Profit | C7: =SUM(Sheet3!C5+Sheet3!C6) -> 1184000
A8: Monthly Profit | B8: Total Profit - Fixed Cost | C8: =Sheet3!C7-Sheet1!B8 -> 1034000

Sheet Sheet4
A1: KPI | B1: Value
A2: Total Revenue | B2: =VLOOKUP(A2,Sheet3!A:C,3,0) -> 2800000
A3: Monthly Profit | B3: =VLOOKUP(A3,Sheet3!A:C,3,0) -> 1034000
A4: ACOS | B4: =(Sheet1!B5/Sheet3!C2) -> 0.25
A5: TACOS | B5: =Sheet1!B5/Sheet3!C4 -> 0.10714286
A6: Profit Margin | B6: =Sheet3!C8/Sheet3!C4 -> 0.36928571

Sheet Sheet5
A1: Metric | B1: Formula | C1: Result
A2: ACOS | B2: Ad Spend ÷ Ad Revenue ×100 | C2: =VLOOKUP(A2,Sheet4!A:B,2,0) -> 0.25
A3: TACOS | B3: Ad Spend ÷ Total Revenue ×100 | C3: =VLOOKUP(A3,Sheet4!A:B,2,0) -> 0.10714286

Sheet Sheet6
A1: Metric | B1: Value
A2: Current Profit | B2: =Sheet3!C7-Sheet1!B8 -> 1034000
A3: Current Ad Spend | B3: =VLOOKUP(Sheet1!A5,Sheet1!A:B,2,0) -> 300000
A4: Break-Even Ad Spend | B4: =SUM(B2+B3) -> 1334000
A5: Break-Even ACOS | B5: =B4/Sheet3!C2 -> 1.1116667

Sheet Sheet7
A1: Scenario | B1: Ad Spend | C1: Ad Units | D1: Profit | E1: Revenue | F1: Ad cost per Unit | G1: net margin | H1: Ad profit | I1: organic profit
A2: Current | B2: 300000 | C2: 1500 | D2: =H2+I2-Sheet1!B8 -> 1034000 | E2: =C2*Sheet1!B2 -> 1200000 | F2: =B2/C2 -> 200 | G2: =Sheet2!C2-Sheet2!C3-Sheet7!$F$2 -> 224 | H2: =G2*C2 -> 336000 | I2: =Sheet2!C6 * Sheet1!B7 -> 848000
A3: High ACOS | B3: 384000 | C3: 1200 | D3: =H3+I3-Sheet1!B8 -> 822800 | E3: =C3*Sheet1!B2 -> 960000 | F3: =B3/C3 -> 320 | G3: =Sheet2!C2-Sheet2!C3-Sheet7!$F$3 -> 104 | H3: =G3*C3 -> 124800 | I3: =Sheet2!C6*Sheet1!B7 -> 848000
A4: Scale Up | B4: 600000 | C4: 2500 | D4: =H4+I4-Sheet1!B8 -> 1158000 | E4: =C4*Sheet1!B2 -> 2000000 | F4: =B4/C4 -> 240 | G4: =Sheet2!C2-Sheet2!C3-$F$4 -> 184 | H4: =G4*C4 -> 460000 | I4: =Sheet2!C6*Sheet1!B7 -> 848000
